main.py
android_vision_agent-1.0.1.dist-info/WHEEL
android_vision_agent-1.0.1.dist-info/entry_points.txt
android_vision_agent-1.0.1.dist-info/top_level.txt
android_vision_agent-1.0.1.dist-info/METADATA
android_vision_agent-1.0.1.dist-info/RECORD
android_vision_agent-1.0.1.dist-info/licenses/LICENSE
vision_agent/api.cpython-311-x86_64-linux-gnu.so
vision_agent/router.cpython-311-x86_64-linux-gnu.so
vision_agent/cli.py
vision_agent/exceptions.cpython-311-x86_64-linux-gnu.so
vision_agent/exceptions.py
vision_agent/config.cpython-311-x86_64-linux-gnu.so
vision_agent/api.py
vision_agent/__main__.py
vision_agent/router.py
vision_agent/config.py
vision_agent/__init__.py
vision_agent/utils/action_executor.py
vision_agent/utils/xml.cpython-311-x86_64-linux-gnu.so
vision_agent/utils/xml.py
vision_agent/utils/image.py
vision_agent/utils/action_executor.cpython-311-x86_64-linux-gnu.so
vision_agent/utils/__init__.py
vision_agent/utils/image.cpython-311-x86_64-linux-gnu.so
vision_agent/license/generator.cpython-311-x86_64-linux-gnu.so
vision_agent/license/validator.py
vision_agent/license/validator.cpython-311-x86_64-linux-gnu.so
vision_agent/license/generator.py
vision_agent/license/__init__.py
vision_agent/modes/displays.py
vision_agent/modes/ocr.cpython-311-x86_64-linux-gnu.so
vision_agent/modes/automate.cpython-311-x86_64-linux-gnu.so
vision_agent/modes/locate_xml.py
vision_agent/modes/llmclient.cpython-311-x86_64-linux-gnu.so
vision_agent/modes/locate_xml.cpython-311-x86_64-linux-gnu.so
vision_agent/modes/diff.cpython-311-x86_64-linux-gnu.so
vision_agent/modes/action.cpython-311-x86_64-linux-gnu.so
vision_agent/modes/diff.py
vision_agent/modes/locate.py
vision_agent/modes/displays.cpython-311-x86_64-linux-gnu.so
vision_agent/modes/locate_ocr.cpython-311-x86_64-linux-gnu.so
vision_agent/modes/ocr.py
vision_agent/modes/locate_ocr.py
vision_agent/modes/__init__.py
vision_agent/modes/action.py
vision_agent/modes/locate.cpython-311-x86_64-linux-gnu.so
vision_agent/modes/automate.py
vision_agent/modes/llmclient.py
vision_agent/device/__init__.py
vision_agent/device/adb/text_input.cpython-311-x86_64-linux-gnu.so
vision_agent/device/adb/displays.py
vision_agent/device/adb/adb_cmd.py
vision_agent/device/adb/devices.py
