Metadata-Version: 2.4
Name: android-vision-agent
Version: 1.0.1
Summary: Android automation with AI vision and natural language
Author: Liu,Lei(tracetronic China)
Requires-Python: >=3.11
License-File: LICENSE
Requires-Dist: openai>=1.0.0
Requires-Dist: Pillow>=10.0.0
Requires-Dist: python-dotenv>=1.0.0
Requires-Dist: uiautomator2>=3.0.0
Provides-Extra: dev
Requires-Dist: pytest>=7.0.0; extra == "dev"
Requires-Dist: pytest-cov>=4.0.0; extra == "dev"
Requires-Dist: Cython>=3.0.0; extra == "dev"
Dynamic: author
Dynamic: license-file
Dynamic: provides-extra
Dynamic: requires-dist
Dynamic: requires-python
Dynamic: summary
